sb_pubsub_kafka/__init__.py
sb_pubsub_kafka/envelope_mapper.py
sb_pubsub_kafka/pub.py
sb_pubsub_kafka/pubsub.py
sb_pubsub_kafka-0.0.3.dist-info/LICENSE
sb_pubsub_kafka-0.0.3.dist-info/METADATA
sb_pubsub_kafka-0.0.3.dist-info/WHEEL
sb_pubsub_kafka-0.0.3.dist-info/top_level.txt
sb_pubsub_kafka-0.0.3.dist-info/RECORD
