Metadata-Version: 2.1
Name: sb-pubsub-kafka
Version: 0.0.3
Summary: A kafka wrapper
Author-email: Stephen Booth <stephen.booth.za@gmail.com>
Classifier: Programming Language :: Python :: 3
Classifier: License :: OSI Approved :: MIT License
Classifier: Operating System :: OS Independent
Requires-Python: >=3.7
License-File: LICENSE
Requires-Dist: confluent-kafka >=2.2.0
